{"data":
[{"id":"MDEwOlJlcG9zaXRvcnkyNDU0NjcyNzQ=",
"name":"Kaznews",
"createdAt":"Aug 18, 2022",
"url":"https://kaznews.vercel.app/",
"description":"Kaznews is a web application based on react js technologies and backend parts on Django rest framework, using api axios. In Kaznews you can write posts if this post is approved by the site administrator, then it is published, it has its own admin panel",
"isFork":true,"languages":[{"name":"HTML","iconifyClass":"logos-html-5"},{"name":"CSS","iconifyClass":"logos-css-3"},
{"name":"JavaScript","iconifyClass":"logos-javascript"},
{"name":"React","iconifyClass":"logos-react"},
{"name":"Python","iconifyClass":"logos-python"},
{"name":"Django-rest-framework","iconifyClass":"logos-django"}]
},
{"id":"MDEwOlJlcG9zaXRvcnkyNjkwNzUwMjM=",
"name":"Translated with by Yandex API",
"createdAt":"Dec 20, 2022",
"url":"https://translate-mu.vercel.app/",
"description":"Translator made using react js and yandex API and bd backend django rest framework ","isFork":false,"languages":[{"name":"HTML","iconifyClass":"logos-html-5"},{"name":"CSS","iconifyClass":"logos-css-3"},{"name":"JavaScript","iconifyClass":"logos-javascript"},{"name":"Django","iconifyClass":"logos-django"},{"name":"React","iconifyClass":"logos-react"}]},
{"id":"MDEwOlJlcG9zaXRvcnkyNjkwNzUwMjM=",
"name":"T-mart, e-commerce",
"createdAt":"Apr 25, 2022",
"url":"http://sanzharsapar.pythonanywhere.com/",
"description":"My second project is also an online store with django 4.0, ajax with the possibility of e-mail confirmation and two admin panels, one for the superadmin and the second for the admins","isFork":false,"languages":[{"name":"HTML","iconifyClass":"logos-html-5"},{"name":"CSS","iconifyClass":"logos-css-3"},{"name":"JavaScript","iconifyClass":"logos-javascript"},{"name":"Python","iconifyClass":"logos-python"},{"name":"Django","iconifyClass":"logos-django"}]},
{"id":"MDEwOlJlcG9zaXRvcnkyNzM1MTI1NTE=",
"name":"Kaznews API docs",
"createdAt":"Aug 18, 2022",
"url":"https://kaznews.pythonanywhere.com/swagger/",
"description":"Kaznews api is a backend part with swagger and redoc documentation(Django Rest Framework)","isFork":false,"languages":[{"name":"Python","iconifyClass":"logos-python"},{"name":"Django-rest-framework","iconifyClass":"logos-django"}]},
{"id":"MDEwOlJlcG9zaXRvcnkxNTU5NTE3NTk=",
"name":"Video Downolader",
"createdAt":"May 19, 2022",
"url":"https://github.com/sanzharsp/youtbe_downolader-for-tkinter",
"description":"Video downloader with ui",
"isFork":false,
"languages":[{"name":"Python","iconifyClass":"logos-python"}]
},
{"id":"MDEwOlJlcG9zaXRvcnkxNTd5NsdEdfdfTk=",
"name":"React Pizza",
"createdAt":"Nov 10, 2022",
"url":"https://react-pizza-self.vercel.app/",
"description":"React Pizza demo site ",
"isFork":false,
"languages":[{"name":"React","iconifyClass":"logos-react"},{"name":"React","iconifyClass":"logos-javascript"}]
}


]


}